pyfskelec/__init__.py
pyfskelec/__main__.py
pyfskelec/client.py
pyfskelec/const.py
pyfskelec/exceptions.py
pyfskelec/models.py
pyfskelec-0.1.4.dist-info/licenses/LICENSE
pyfskelec-0.1.4.dist-info/METADATA
pyfskelec-0.1.4.dist-info/WHEEL
pyfskelec-0.1.4.dist-info/entry_points.txt
pyfskelec-0.1.4.dist-info/top_level.txt
pyfskelec-0.1.4.dist-info/RECORD
