Metadata-Version: 2.4
Name: pyfskelec
Version: 0.1.4
Summary: Unofficial client library for the ArmME / MiFalcon (pyfskelec) API.
Home-page: https://github.com/RenierM26/pyfskelec/
Author: Renier Moorcroft
Author-email: RenierM26@users.github.com
License: GPL-3.0 license
Requires-Python: >=3.10
License-File: LICENSE
Requires-Dist: requests
Dynamic: author
Dynamic: author-email
Dynamic: description
Dynamic: home-page
Dynamic: license
Dynamic: license-file
Dynamic: requires-dist
Dynamic: requires-python
Dynamic: summary
